video_cover_mcp/__init__.py
video_cover_mcp/main.py
mcpcn_video_cover_mcp-0.2.7.dist-info/METADATA
mcpcn_video_cover_mcp-0.2.7.dist-info/WHEEL
mcpcn_video_cover_mcp-0.2.7.dist-info/entry_points.txt
mcpcn_video_cover_mcp-0.2.7.dist-info/RECORD
